MANIFEST.in
README.md
setup.py
django_hashcash/__init__.py
django_hashcash/forms.py
django_hashcash.egg-info/PKG-INFO
django_hashcash.egg-info/SOURCES.txt
django_hashcash.egg-info/dependency_links.txt
django_hashcash.egg-info/not-zip-safe
django_hashcash.egg-info/top_level.txt
django_hashcash/static/django_hashcash/jquery.hashcash.io/jquery.hashcash.io.min.css
django_hashcash/static/django_hashcash/jquery.hashcash.io/jquery.hashcash.io.min.js
django_hashcash/templates/django_hashcash/login.html
django_hashcash/templatetags/__init__.py
django_hashcash/templatetags/django_hashcash_tags.py