Metadata-Version: 1.1
Name: django-hashcash
Version: 0.2.1
Summary: Adds HashCash.IO "proof-of-work" control to django login form.
Home-page: https://github.com/mkoistinen/django-hashcash
Author: Martin Koistinen
Author-email: mkoistinen@gmail.com
License: LICENSE.txt
Platform: OS Independent
Classifier: Development Status :: 2 - Pre-Alpha
Classifier: Environment :: Web Environment
Classifier: Framework :: Django
Classifier: Intended Audience :: Developers
Classifier: License :: OSI Approved :: BSD License
Classifier: Operating System :: OS Independent
Classifier: Programming Language :: Python
Classifier: Topic :: Internet :: WWW/HTTP :: Dynamic Content
Classifier: Topic :: Software Development
Classifier: Topic :: Software Development :: Libraries :: Application Frameworks
